{"nodes": [{"id": "workflows_deploy_prod_cicd_pipeline", "label": "Deploy \u2014 Production CI/CD Pipeline", "file_type": "code", "source_file": ".github/workflows/deploy-prod.yml", "source_location": "line 1", "source_url": null, "captured_at": null, "author": null, "contributor": null}, {"id": "workflows_deploy_prod_build_push_job", "label": "Build & Push Release Images Job (OCI Registry)", "file_type": "code", "source_file": ".github/workflows/deploy-prod.yml", "source_location": "line 13", "source_url": null, "captured_at": null, "author": null, "contributor": null}, {"id": "workflows_deploy_prod_deploy_production_job", "label": "Deploy to Production Job (SSH + docker compose + prisma migrate)", "file_type": "code", "source_file": ".github/workflows/deploy-prod.yml", "source_location": "line 33", "source_url": null, "captured_at": null, "author": null, "contributor": null}, {"id": "workflows_deploy_prod_smoke_test", "label": "Post-deploy Smoke Test (/v1/health + /v1/metrics)", "file_type": "code", "source_file": ".github/workflows/deploy-prod.yml", "source_location": "line 56", "source_url": null, "captured_at": null, "author": null, "contributor": null}, {"id": "workflows_deploy_prod_slack_notify", "label": "Slack Deploy Notifications (success/failure webhook)", "file_type": "code", "source_file": ".github/workflows/deploy-prod.yml", "source_location": "line 63", "source_url": null, "captured_at": null, "author": null, "contributor": null}], "edges": [{"source": "workflows_deploy_prod_cicd_pipeline", "target": "workflows_deploy_prod_build_push_job", "relation": "implements", "confidence": "EXTRACTED", "confidence_score": 1.0, "source_file": ".github/workflows/deploy-prod.yml", "source_location": "line 13", "weight": 1.0}, {"source": "workflows_deploy_prod_cicd_pipeline", "target": "workflows_deploy_prod_deploy_production_job", "relation": "implements", "confidence": "EXTRACTED", "confidence_score": 1.0, "source_file": ".github/workflows/deploy-prod.yml", "source_location": "line 33", "weight": 1.0}, {"source": "workflows_deploy_prod_deploy_production_job", "target": "workflows_deploy_prod_build_push_job", "relation": "references", "confidence": "EXTRACTED", "confidence_score": 1.0, "source_file": ".github/workflows/deploy-prod.yml", "source_location": "line 37", "weight": 1.0}, {"source": "workflows_deploy_prod_deploy_production_job", "target": "workflows_deploy_prod_smoke_test", "relation": "implements", "confidence": "EXTRACTED", "confidence_score": 1.0, "source_file": ".github/workflows/deploy-prod.yml", "source_location": "line 56", "weight": 1.0}, {"source": "workflows_deploy_prod_deploy_production_job", "target": "workflows_deploy_prod_slack_notify", "relation": "implements", "confidence": "EXTRACTED", "confidence_score": 1.0, "source_file": ".github/workflows/deploy-prod.yml", "source_location": "line 63", "weight": 1.0}, {"source": "workflows_deploy_prod_build_push_job", "target": "backend_changelog_nestjs_backend", "relation": "references", "confidence": "EXTRACTED", "confidence_score": 1.0, "source_file": ".github/workflows/deploy-prod.yml", "source_location": "line 24", "weight": 1.0}, {"source": "workflows_deploy_prod_build_push_job", "target": "dsp_service_changelog_fastapi_dsp", "relation": "references", "confidence": "EXTRACTED", "confidence_score": 1.0, "source_file": ".github/workflows/deploy-prod.yml", "source_location": "line 24", "weight": 1.0}, {"source": "workflows_deploy_prod_smoke_test", "target": "backend_changelog_nestjs_backend", "relation": "references", "confidence": "EXTRACTED", "confidence_score": 1.0, "source_file": ".github/workflows/deploy-prod.yml", "source_location": "line 59", "weight": 1.0}], "hyperedges": [{"id": "hyperedge_cicd_prod_deploy_flow", "label": "Production Deploy Flow \u2014 build+push \u2192 SSH deploy + prisma migrate \u2192 smoke test \u2192 Slack notify", "nodes": ["workflows_deploy_prod_build_push_job", "workflows_deploy_prod_deploy_production_job", "workflows_deploy_prod_smoke_test", "workflows_deploy_prod_slack_notify"], "relation": "form", "confidence": "EXTRACTED", "confidence_score": 1.0, "source_file": ".github/workflows/deploy-prod.yml"}]}